main.py
transactions_mcp-1.0.0.dist-info/METADATA
transactions_mcp-1.0.0.dist-info/WHEEL
transactions_mcp-1.0.0.dist-info/top_level.txt
transactions_mcp-1.0.0.dist-info/RECORD
