Metadata-Version: 2.4
Name: transactions-mcp
Version: 1.0.0
Summary: Add your description here
Requires-Python: >=3.12
Requires-Dist: dotenv>=0.9.9
Requires-Dist: logging>=0.4.9.6
Requires-Dist: mcp>=1.25.0
Requires-Dist: requests>=2.32.5
